<?xml version="1.0" encoding="UTF-8"?>
<FormData version="8.0" designer="8.1" buildNumber="200809101301">
  <ColorPalette C0="0,0,0" C1="128,0,0" C2="0,128,0" C3="128,128,0" C4="0,0,128" C5="128,0,128" C6="0,128,128" C7="128,128,128" C8="192,192,192" C9="255,0,0" C10="0,255,0" C11="255,255,0" C12="0,0,255" C13="255,0,255" C14="0,255,255" C15="255,255,255" />
  <PageColorLine C0="0" C1="0" C2="0" C3="0" C4="0" C5="0" C6="0" C7="0" C8="0" C9="0" C10="0" C11="0" C12="0" C13="0" C14="0" C15="0" C16="0" C17="0" C18="0" C19="0" C20="0" C21="0" C22="0" C23="0" C24="0" C25="0" C26="0" C27="0" C28="0" C29="0" />
  <PageColorField C0="0" C1="0" C2="0" C3="0" C4="0" C5="0" C6="0" C7="0" C8="0" C9="0" C10="0" C11="0" C12="0" C13="0" C14="0" C15="0" C16="0" C17="0" C18="0" C19="0" C20="0" C21="0" C22="0" C23="0" C24="0" C25="0" C26="0" C27="0" C28="0" C29="0" />
  <PageColorBoxLine C0="0" C1="0" C2="0" C3="0" C4="0" C5="0" C6="0" C7="0" C8="0" C9="0" C10="0" C11="0" C12="0" C13="0" C14="0" C15="0" C16="0" C17="0" C18="0" C19="0" C20="0" C21="0" C22="0" C23="0" C24="0" C25="0" C26="0" C27="0" C28="0" C29="0" />
  <PageColorBoxPaint C0="0" C1="0" C2="0" C3="0" C4="0" C5="0" C6="0" C7="0" C8="0" C9="0" C10="0" C11="0" C12="0" C13="0" C14="0" C15="0" C16="0" C17="0" C18="0" C19="0" C20="0" C21="0" C22="0" C23="0" C24="0" C25="0" C26="0" C27="0" C28="0" C29="0" />
  <PageColorRecordLine C0="0" C1="0" C2="0" C3="0" C4="0" C5="0" C6="0" C7="0" C8="0" C9="0" C10="0" C11="0" C12="0" C13="0" C14="0" C15="0" C16="0" C17="0" C18="0" C19="0" C20="0" C21="0" C22="0" C23="0" C24="0" C25="0" C26="0" C27="0" C28="0" C29="0" />
  <PageColorRecordPaint C0="0" C1="0" C2="0" C3="0" C4="0" C5="0" C6="0" C7="0" C8="0" C9="0" C10="0" C11="0" C12="0" C13="0" C14="0" C15="0" C16="0" C17="0" C18="0" C19="0" C20="0" C21="0" C22="0" C23="0" C24="0" C25="0" C26="0" C27="0" C28="0" C29="0" />
  <PageColorBitmap C0="0" C1="0" C2="0" C3="0" C4="0" C5="0" C6="0" C7="0" C8="0" C9="0" C10="0" C11="0" C12="0" C13="0" C14="0" C15="0" C16="0" C17="0" C18="0" C19="0" C20="0" C21="0" C22="0" C23="0" C24="0" C25="0" C26="0" C27="0" C28="0" C29="0" />
  <PageColorText C0="0" C1="0" C2="0" C3="0" C4="0" C5="0" C6="0" C7="0" C8="0" C9="0" C10="0" C11="0" C12="0" C13="0" C14="0" C15="0" C16="0" C17="0" C18="0" C19="0" C20="0" C21="0" C22="0" C23="0" C24="0" C25="0" C26="0" C27="0" C28="0" C29="0" />
  <PageColorBarcode C0="0" C1="0" C2="0" C3="0" C4="0" C5="0" C6="0" C7="0" C8="0" C9="0" C10="0" C11="0" C12="0" C13="0" C14="0" C15="0" C16="0" C17="0" C18="0" C19="0" C20="0" C21="0" C22="0" C23="0" C24="0" C25="0" C26="0" C27="0" C28="0" C29="0" />
  <PageColorSubForm C0="0" C1="0" C2="0" C3="0" C4="0" C5="0" C6="0" C7="0" C8="0" C9="0" C10="0" C11="0" C12="0" C13="0" C14="0" C15="0" C16="0" C17="0" C18="0" C19="0" C20="0" C21="0" C22="0" C23="0" C24="0" C25="0" C26="0" C27="0" C28="0" C29="0" />
  <DefaultColors C0="#000000" C1="#800000" C2="#008000" C3="#808000" C4="#000080" C5="#800080" C6="#008080" C7="#808080" C8="#c0c0c0" C9="#ff0000" C10="#00ff00" C11="#ffff00" C12="#0000ff" C13="#ff00ff" C14="#00ffff" C15="#ffffff" />
  <BarcodeElement>
    <Code128 Bar1="1" Bar2="1" Bar3="1" Bar4="1" Space1="1" Space2="1" Space3="1" Space4="1" />
    <Code39 NarrowBar="1" WideBar="1" NarrowSpace="1" WideSpace="1" CharGap="1" />
    <NW7 NarrowBar="1" WideBar="1" NarrowSpace="1" WideSpace="1" CharGap="1" />
    <ITF NarrowBar="1" WideBar="1" NarrowSpace="1" WideSpace="1" />
    <JAN Bar1="1" Bar2="1" Bar3="1" Bar4="1" Space1="1" Space2="1" Space3="1" Space4="1" />
  </BarcodeElement>
  <LayerInfo Number="22" Visible="true" Enable="true" />
  <LayerInfo Number="21" Visible="true" Enable="true" />
  <LayerInfo Number="20" Visible="true" Enable="true" />
  <LayerInfo Number="40" Visible="true" Enable="true" />
  <LayerInfo Number="35" Visible="true" Enable="true" />
  <LayerInfo Number="12" Visible="true" Enable="true" />
  <LayerInfo Number="11" Visible="true" Enable="true" />
  <LayerInfo Number="10" Visible="true" Enable="true" />
  <LayerInfo Number="32" Visible="true" Enable="true" />
  <LayerInfo Number="31" Visible="true" Enable="true" />
  <LayerInfo Number="30" Visible="true" Enable="true" />
  <LayerInfo Number="6" Visible="true" Enable="true" />
  <LayerInfo Number="5" Visible="true" Enable="true" />
  <LayerInfo Number="50" Visible="true" Enable="true" />
  <LayerInfo Number="4" Visible="true" Enable="true" />
  <LayerInfo Number="23" Visible="true" Enable="true" />
  <FontSetting count="2" hanCount="3" Name1="ＭＳ 明朝" Name2="ＭＳ ゴシック" HanName1="なし" HanName2="Courier New" HanName3="OCRB" />
  <Paper outputKind="0" size="2" direction="1" renLength="1" renWidth="15" adjustX="0" adjustXmm="0" adjustYmm="0" adjustY="0" fUseColor="true" copyCount="1" printCount="1" pagingMode="false" strLinkFormName="" strPaperCode="" strFormTitle="" strFormTitleKana="" duplexMode="0" duplexMargin="0" bin="0" scale="0" stackMode="0" zenPitch="0" barDensity="1" fBarAdjust="false" fBarUseElement="false" freeWidth="105" freeHeight="148" resolution="400" sizeUnit="1" paperColor="255,255,255" frmCompatible="false" strCountry="Japan" countryIndex="0" countryIndexReal="0" strComment="" />
  <Field name="TITLE" strComment="タイトル" strLinkFieldName="" x="557" y="200" charCount="60" charCountDisp="60" bufferLen="0" charType="0" pitch="0" fixPitch="false" fontNum="1" hanFontNum="0" point="14" type="0" editStyle="0" strCalcFormula="" strEditFormula="" vertRatio="1" vertRatioN="1" horzRatio="1" horzRatioN="1" direction="0" rotation="0" maskFlag="false" lockFlag="false" keyNum="0" isDescending="false" pageFeed="false" strHeaderRecName="" strTotalRecName="" onlyFirstPage="false" onlyLastPage="false" printLastOfGroup="false" groupSuppress="false" groupSuppressFree="false" centeringOnDuplicated="false" suppressLineOnDuplicated="false" clearAccumulateCount="false" clearPageCount="false" frmCompatible="true" graphicMode="false" bold="false" italic="false" outline="false" outlineWidth="1" strImage="" whiteChar="false" shadow="false" useGradientPaint="false" colorGradient1="1" colorGradient2="1" gradientKind="0" annotationLevel="0" commonPage="true" layerNumber="31" locked="false" groupIndex="0" colorIndexes="0" />
  <Text name="Text2" x="3075" y="473" strText="備考" pitch="0" fixPitch="false" fontNum="0" hanFontNum="0" point="8" vertRatio="1" vertRatioN="1" horzRatio="1" horzRatioN="1" direction="0" rotation="0" frmCompatible="true" graphicMode="false" bold="false" italic="false" outline="false" outlineWidth="1" strImage="" whiteChar="false" shadow="false" useGradientPaint="false" colorGradient1="1" colorGradient2="1" gradientKind="0" textColor="1" commonPage="false" layerNumber="30" locked="false" groupIndex="0" pageFlags="true" colorIndexes="0" />
  <Line name="Line2" x1="3028" y1="356" x2="3028" y2="634" lineWidth="1" lineWidthDot="1" lineType="0" frmCompatible="true" graphicMode="false" arrowPos="0" arrowSide="0" arrowType="0" arrowAngle="30" arrowSize="80" curvePattern="0" curveTileType="0" curveTileLineWidth="4" curveTileLineDist="64" curveColor1="1" curveColor2="1" hvOnly="true" commonPage="false" layerNumber="21" locked="false" groupIndex="0" pageFlags="true" colorIndexes="0" />
  <Text name="Text3" x="2151" y="375" strText="修学金" pitch="0" fixPitch="false" fontNum="0" hanFontNum="0" point="8" vertRatio="1" vertRatioN="1" horzRatio="1" horzRatioN="1" direction="0" rotation="0" frmCompatible="true" graphicMode="false" bold="false" italic="false" outline="false" outlineWidth="1" strImage="" whiteChar="false" shadow="false" useGradientPaint="false" colorGradient1="1" colorGradient2="1" gradientKind="0" textColor="1" commonPage="true" layerNumber="12" locked="false" groupIndex="0" colorIndexes="0" />
  <Text name="Text4" x="2727" y="375" strText="支度金" pitch="0" fixPitch="false" fontNum="0" hanFontNum="0" point="8" vertRatio="1" vertRatioN="1" horzRatio="1" horzRatioN="1" direction="0" rotation="0" frmCompatible="true" graphicMode="false" bold="false" italic="false" outline="false" outlineWidth="1" strImage="" whiteChar="false" shadow="false" useGradientPaint="false" colorGradient1="1" colorGradient2="1" gradientKind="0" textColor="1" commonPage="true" layerNumber="12" locked="false" groupIndex="0" colorIndexes="0" />
  <Text name="Text5" x="1621" y="451" strText="学年" pitch="0" fixPitch="false" fontNum="0" hanFontNum="0" point="8" vertRatio="1" vertRatioN="1" horzRatio="1" horzRatioN="1" direction="1" rotation="0" frmCompatible="true" graphicMode="false" bold="false" italic="false" outline="false" outlineWidth="1" strImage="" whiteChar="false" shadow="false" useGradientPaint="false" colorGradient1="1" colorGradient2="1" gradientKind="0" textColor="1" commonPage="true" layerNumber="12" locked="false" groupIndex="0" colorIndexes="0" />
  <Text name="Text6" x="1717" y="451" strText="修学生" pitch="0" fixPitch="false" fontNum="0" hanFontNum="0" point="8" vertRatio="1" vertRatioN="1" horzRatio="1" horzRatioN="1" direction="0" rotation="0" frmCompatible="true" graphicMode="false" bold="false" italic="false" outline="false" outlineWidth="1" strImage="" whiteChar="false" shadow="false" useGradientPaint="false" colorGradient1="1" colorGradient2="1" gradientKind="0" textColor="1" commonPage="true" layerNumber="12" locked="false" groupIndex="0" colorIndexes="0" />
  <Text name="Text7" x="2184" y="453" strText="貸与希望期間" pitch="0" fixPitch="false" fontNum="0" hanFontNum="0" point="8" vertRatio="1" vertRatioN="1" horzRatio="1" horzRatioN="1" direction="0" rotation="0" frmCompatible="true" graphicMode="false" bold="false" italic="false" outline="false" outlineWidth="1" strImage="" whiteChar="false" shadow="false" useGradientPaint="false" colorGradient1="1" colorGradient2="1" gradientKind="0" textColor="1" commonPage="true" layerNumber="12" locked="false" groupIndex="0" colorIndexes="0" />
  <Text name="Text8" x="497" y="473" strText="学校名称" pitch="0" fixPitch="false" fontNum="0" hanFontNum="0" point="8" vertRatio="1" vertRatioN="1" horzRatio="1" horzRatioN="1" direction="0" rotation="0" frmCompatible="true" graphicMode="false" bold="false" italic="false" outline="false" outlineWidth="1" strImage="" whiteChar="false" shadow="false" useGradientPaint="false" colorGradient1="1" colorGradient2="1" gradientKind="0" textColor="1" commonPage="true" layerNumber="12" locked="false" groupIndex="0" colorIndexes="0" />
  <Text name="Text9" x="927" y="473" strText="課程" pitch="0" fixPitch="false" fontNum="0" hanFontNum="0" point="8" vertRatio="1" vertRatioN="1" horzRatio="1" horzRatioN="1" direction="0" rotation="0" frmCompatible="true" graphicMode="false" bold="false" italic="false" outline="false" outlineWidth="1" strImage="" whiteChar="false" shadow="false" useGradientPaint="false" colorGradient1="1" colorGradient2="1" gradientKind="0" textColor="1" commonPage="true" layerNumber="12" locked="false" groupIndex="0" colorIndexes="0" />
  <Text name="Text10" x="1246" y="473" strText="修学生氏名" pitch="0" fixPitch="false" fontNum="0" hanFontNum="0" point="8" vertRatio="1" vertRatioN="1" horzRatio="1" horzRatioN="1" direction="0" rotation="0" frmCompatible="true" graphicMode="false" bold="false" italic="false" outline="false" outlineWidth="1" strImage="" whiteChar="false" shadow="false" useGradientPaint="false" colorGradient1="1" colorGradient2="1" gradientKind="0" textColor="1" commonPage="true" layerNumber="12" locked="false" groupIndex="0" colorIndexes="0" />
  <Text name="Text11" x="1915" y="491" strText="貸与希" pitch="0" fixPitch="false" fontNum="0" hanFontNum="0" point="8" vertRatio="1" vertRatioN="1" horzRatio="1" horzRatioN="1" direction="0" rotation="0" frmCompatible="true" graphicMode="false" bold="false" italic="false" outline="false" outlineWidth="1" strImage="" whiteChar="false" shadow="false" useGradientPaint="false" colorGradient1="1" colorGradient2="1" gradientKind="0" textColor="1" commonPage="true" layerNumber="12" locked="false" groupIndex="0" colorIndexes="0" />
  <Text name="Text12" x="2607" y="491" strText="修学生" pitch="0" fixPitch="false" fontNum="0" hanFontNum="0" point="8" vertRatio="1" vertRatioN="1" horzRatio="1" horzRatioN="1" direction="0" rotation="0" frmCompatible="true" graphicMode="false" bold="false" italic="false" outline="false" outlineWidth="1" strImage="" whiteChar="false" shadow="false" useGradientPaint="false" colorGradient1="1" colorGradient2="1" gradientKind="0" textColor="1" commonPage="true" layerNumber="12" locked="false" groupIndex="0" colorIndexes="0" />
  <Text name="Text13" x="2867" y="491" strText="貸与" pitch="0" fixPitch="false" fontNum="0" hanFontNum="0" point="8" vertRatio="1" vertRatioN="1" horzRatio="1" horzRatioN="1" direction="0" rotation="0" frmCompatible="true" graphicMode="false" bold="false" italic="false" outline="false" outlineWidth="1" strImage="" whiteChar="false" shadow="false" useGradientPaint="false" colorGradient1="1" colorGradient2="1" gradientKind="0" textColor="1" commonPage="true" layerNumber="12" locked="false" groupIndex="0" colorIndexes="0" />
  <Text name="Text14" x="1739" y="495" strText="番号" pitch="0" fixPitch="false" fontNum="0" hanFontNum="0" point="8" vertRatio="1" vertRatioN="1" horzRatio="1" horzRatioN="1" direction="0" rotation="0" frmCompatible="true" graphicMode="false" bold="false" italic="false" outline="false" outlineWidth="1" strImage="" whiteChar="false" shadow="false" useGradientPaint="false" colorGradient1="1" colorGradient2="1" gradientKind="0" textColor="1" commonPage="true" layerNumber="12" locked="false" groupIndex="0" colorIndexes="0" />
  <Text name="Text15" x="1915" y="535" strText="望月額" pitch="0" fixPitch="false" fontNum="0" hanFontNum="0" point="8" vertRatio="1" vertRatioN="1" horzRatio="1" horzRatioN="1" direction="0" rotation="0" frmCompatible="true" graphicMode="false" bold="false" italic="false" outline="false" outlineWidth="1" strImage="" whiteChar="false" shadow="false" useGradientPaint="false" colorGradient1="1" colorGradient2="1" gradientKind="0" textColor="1" commonPage="true" layerNumber="12" locked="false" groupIndex="0" colorIndexes="0" />
  <Text name="Text16" x="2629" y="535" strText="番号" pitch="0" fixPitch="false" fontNum="0" hanFontNum="0" point="8" vertRatio="1" vertRatioN="1" horzRatio="1" horzRatioN="1" direction="0" rotation="0" frmCompatible="true" graphicMode="false" bold="false" italic="false" outline="false" outlineWidth="1" strImage="" whiteChar="false" shadow="false" useGradientPaint="false" colorGradient1="1" colorGradient2="1" gradientKind="0" textColor="1" commonPage="true" layerNumber="12" locked="false" groupIndex="0" colorIndexes="0" />
  <Text name="Text17" x="2845" y="535" strText="希望額" pitch="0" fixPitch="false" fontNum="0" hanFontNum="0" point="8" vertRatio="1" vertRatioN="1" horzRatio="1" horzRatioN="1" direction="0" rotation="0" frmCompatible="true" graphicMode="false" bold="false" italic="false" outline="false" outlineWidth="1" strImage="" whiteChar="false" shadow="false" useGradientPaint="false" colorGradient1="1" colorGradient2="1" gradientKind="0" textColor="1" commonPage="true" layerNumber="12" locked="false" groupIndex="0" colorIndexes="0" />
  <Text name="Text18" x="2155" y="553" strText="(始)" pitch="0" fixPitch="false" fontNum="0" hanFontNum="0" point="8" vertRatio="1" vertRatioN="1" horzRatio="1" horzRatioN="1" direction="0" rotation="0" frmCompatible="true" graphicMode="false" bold="false" italic="false" outline="false" outlineWidth="1" strImage="" whiteChar="false" shadow="false" useGradientPaint="false" colorGradient1="1" colorGradient2="1" gradientKind="0" textColor="1" commonPage="true" layerNumber="12" locked="false" groupIndex="0" colorIndexes="0" />
  <Text name="Text19" x="2391" y="553" strText="(終)" pitch="0" fixPitch="false" fontNum="0" hanFontNum="0" point="8" vertRatio="1" vertRatioN="1" horzRatio="1" horzRatioN="1" direction="0" rotation="0" frmCompatible="true" graphicMode="false" bold="false" italic="false" outline="false" outlineWidth="1" strImage="" whiteChar="false" shadow="false" useGradientPaint="false" colorGradient1="1" colorGradient2="1" gradientKind="0" textColor="1" commonPage="true" layerNumber="12" locked="false" groupIndex="0" colorIndexes="0" />
  <Line name="Line3" x1="336" y1="356" x2="336" y2="634" lineWidth="1" lineWidthDot="1" lineType="0" frmCompatible="true" graphicMode="false" arrowPos="0" arrowSide="0" arrowType="0" arrowAngle="30" arrowSize="80" curvePattern="0" curveTileType="0" curveTileLineWidth="4" curveTileLineDist="64" curveColor1="1" curveColor2="1" hvOnly="true" commonPage="true" layerNumber="11" locked="false" groupIndex="0" colorIndexes="0" />
  <Line name="Line4" x1="830" y1="356" x2="830" y2="634" lineWidth="1" lineWidthDot="1" lineType="0" frmCompatible="true" graphicMode="false" arrowPos="0" arrowSide="0" arrowType="0" arrowAngle="30" arrowSize="80" curvePattern="0" curveTileType="0" curveTileLineWidth="4" curveTileLineDist="64" curveColor1="1" curveColor2="1" hvOnly="true" commonPage="true" layerNumber="11" locked="false" groupIndex="0" colorIndexes="0" />
  <Line name="Line5" x1="1108" y1="356" x2="1108" y2="634" lineWidth="1" lineWidthDot="1" lineType="0" frmCompatible="true" graphicMode="false" arrowPos="0" arrowSide="0" arrowType="0" arrowAngle="30" arrowSize="80" curvePattern="0" curveTileType="0" curveTileLineWidth="4" curveTileLineDist="64" curveColor1="1" curveColor2="1" hvOnly="true" commonPage="true" layerNumber="11" locked="false" groupIndex="0" colorIndexes="0" />
  <Line name="Line6" x1="1602" y1="356" x2="1602" y2="634" lineWidth="1" lineWidthDot="1" lineType="0" frmCompatible="true" graphicMode="false" arrowPos="0" arrowSide="0" arrowType="0" arrowAngle="30" arrowSize="80" curvePattern="0" curveTileType="0" curveTileLineWidth="4" curveTileLineDist="64" curveColor1="1" curveColor2="1" hvOnly="true" commonPage="true" layerNumber="11" locked="false" groupIndex="0" colorIndexes="0" />
  <Line name="Line7" x1="1682" y1="356" x2="1682" y2="634" lineWidth="1" lineWidthDot="1" lineType="0" frmCompatible="true" graphicMode="false" arrowPos="0" arrowSide="0" arrowType="0" arrowAngle="30" arrowSize="80" curvePattern="0" curveTileType="0" curveTileLineWidth="4" curveTileLineDist="64" curveColor1="1" curveColor2="1" hvOnly="true" commonPage="true" layerNumber="11" locked="false" groupIndex="0" colorIndexes="0" />
  <Line name="Line8" x1="1880" y1="356" x2="1880" y2="634" lineWidth="1" lineWidthDot="1" lineType="0" frmCompatible="true" graphicMode="false" arrowPos="0" arrowSide="0" arrowType="0" arrowAngle="30" arrowSize="80" curvePattern="0" curveTileType="0" curveTileLineWidth="4" curveTileLineDist="64" curveColor1="1" curveColor2="1" hvOnly="true" commonPage="true" layerNumber="11" locked="false" groupIndex="0" colorIndexes="0" />
  <Line name="Line9" x1="2554" y1="356" x2="2554" y2="634" lineWidth="1" lineWidthDot="1" lineType="0" frmCompatible="true" graphicMode="false" arrowPos="0" arrowSide="0" arrowType="0" arrowAngle="30" arrowSize="80" curvePattern="0" curveTileType="0" curveTileLineWidth="4" curveTileLineDist="64" curveColor1="1" curveColor2="1" hvOnly="true" commonPage="true" layerNumber="11" locked="false" groupIndex="0" colorIndexes="0" />
  <Line name="Line10" x1="1880" y1="434" x2="3028" y2="434" lineWidth="1" lineWidthDot="1" lineType="0" frmCompatible="true" graphicMode="false" arrowPos="0" arrowSide="0" arrowType="0" arrowAngle="30" arrowSize="80" curvePattern="0" curveTileType="0" curveTileLineWidth="4" curveTileLineDist="64" curveColor1="1" curveColor2="1" hvOnly="true" commonPage="true" layerNumber="11" locked="false" groupIndex="0" colorIndexes="0" />
  <Line name="Line11" x1="2078" y1="434" x2="2078" y2="632" lineWidth="1" lineWidthDot="1" lineType="0" frmCompatible="true" graphicMode="false" arrowPos="0" arrowSide="0" arrowType="0" arrowAngle="30" arrowSize="80" curvePattern="0" curveTileType="0" curveTileLineWidth="4" curveTileLineDist="64" curveColor1="1" curveColor2="1" hvOnly="true" commonPage="true" layerNumber="11" locked="false" groupIndex="0" colorIndexes="0" />
  <Line name="Line12" x1="2792" y1="434" x2="2792" y2="632" lineWidth="1" lineWidthDot="1" lineType="0" frmCompatible="true" graphicMode="false" arrowPos="0" arrowSide="0" arrowType="0" arrowAngle="30" arrowSize="80" curvePattern="0" curveTileType="0" curveTileLineWidth="4" curveTileLineDist="64" curveColor1="1" curveColor2="1" hvOnly="true" commonPage="true" layerNumber="11" locked="false" groupIndex="0" colorIndexes="0" />
  <Line name="Line13" x1="2078" y1="514" x2="2554" y2="514" lineWidth="1" lineWidthDot="1" lineType="0" frmCompatible="true" graphicMode="false" arrowPos="0" arrowSide="0" arrowType="0" arrowAngle="30" arrowSize="80" curvePattern="0" curveTileType="0" curveTileLineWidth="4" curveTileLineDist="64" curveColor1="1" curveColor2="1" hvOnly="true" commonPage="true" layerNumber="11" locked="false" groupIndex="0" colorIndexes="0" />
  <Line name="Line14" x1="2316" y1="514" x2="2316" y2="634" lineWidth="1" lineWidthDot="1" lineType="0" frmCompatible="true" graphicMode="false" arrowPos="0" arrowSide="0" arrowType="0" arrowAngle="30" arrowSize="80" curvePattern="0" curveTileType="0" curveTileLineWidth="4" curveTileLineDist="64" curveColor1="1" curveColor2="1" hvOnly="true" commonPage="true" layerNumber="11" locked="false" groupIndex="0" colorIndexes="0" />
  <Box name="Box2" x1="236" y1="356" x2="3206" y2="632" fillingOutline="true" lineType="0" lineWidth="1" lineWidthDot="1" frameKind="0" topEdge="true" lineWidthUP="0" lineWidthDotUP="1" lineTypeUP="0" bottomEdge="true" lineWidthDN="0" lineWidthDotDN="1" lineTypeDN="0" leftEdge="true" lineWidthL="0" lineWidthDotL="1" lineTypeL="0" rightEdge="true" lineWidthR="0" lineWidthDotR="1" lineTypeR="0" cornerType="0" leftUpperCorner="false" leftLowerCorner="false" rightUpperCorner="false" rightLowerCorner="false" cornerRadius="0" direction="0" frmCompatible="true" graphicMode="false" curvePattern="0" curveTileType="0" curveTileLineWidth="4" curveTileLineDist="64" curveGradientI="0" curveColor1="1" curveColor2="1" fillingType="0" grayScaleType="0" lineTileType="0" tileLineWidth="4" tileLineDistance="64" tileImageFilePath="" tileImageFitting="false" gradientX1="0" gradientY1="0" gradientX2="100" gradientY2="0" gradientCyclic="false" gradientI="0" gradientX="0" roundGradientX="1000" roundGradientY="1000" roundGradientRadius="2000" interiorBgColor="1" gradientColor1="1" gradientColor2="1" wordPaint="false" forSubFormOrRecord="false" commonPage="true" layerNumber="10" locked="false" groupIndex="0" colorIndexes="0" paintColorIndexes="0" />
  <SubForm name="SUBFORM1" linkName="" x1="236" y1="632" x2="3206" y2="4534" direction="1" noPrintOnEmpty="false" keyDifferSuppress="false" frameSizeFix="false" printMode="0" commonPage="false" layerNumber="5" locked="false" groupIndex="0" colorIndexes="0">
    <SubProperties.Box name="Box1" x1="236" y1="632" x2="3206" y2="4534" fillingOutline="false" lineType="0" lineWidth="1" lineWidthDot="1" frameKind="0" topEdge="true" lineWidthUP="0" lineWidthDotUP="1" lineTypeUP="0" bottomEdge="true" lineWidthDN="0" lineWidthDotDN="1" lineTypeDN="0" leftEdge="true" lineWidthL="0" lineWidthDotL="1" lineTypeL="0" rightEdge="true" lineWidthR="0" lineWidthDotR="1" lineTypeR="0" cornerType="0" leftUpperCorner="true" leftLowerCorner="true" rightUpperCorner="true" rightLowerCorner="true" cornerRadius="50" direction="0" frmCompatible="true" graphicMode="false" curvePattern="0" curveTileType="0" curveTileLineWidth="4" curveTileLineDist="64" curveGradientI="0" curveColor1="1" curveColor2="1" fillingType="0" grayScaleType="0" lineTileType="0" tileLineWidth="4" tileLineDistance="64" tileImageFilePath="" tileImageFitting="false" gradientX1="0" gradientY1="0" gradientX2="100" gradientY2="0" gradientCyclic="false" gradientI="0" gradientX="0" roundGradientX="1000" roundGradientY="1000" roundGradientRadius="2000" interiorBgColor="1" gradientColor1="1" gradientColor2="1" wordPaint="false" forSubFormOrRecord="true" commonPage="true" layerNumber="0" groupIndex="0" colorIndexes="0" paintColorIndexes="0" subProperties="true" />
    <Record name="RECORD1" x1="236" y1="634" x2="3206" y2="712" type="0" forcePrint="false" topOfDetail="false" printOnTopOfPage="false" notPrintWhenDetailOne="false" notPrintOnEmpty="true" paintLineSelection="0" strLineSelection="1" heightUnit="0" height="78" autoLinkPitch="1.2" fixedPosition="false" displayLineCount="1" commonPage="false" layerNumber="6" locked="false" groupIndex="0" colorIndexes="0" paintColorIndexes="0">
      <SubProperties.Box name="Box1" x1="236" y1="634" x2="3206" y2="712" fillingOutline="true" lineType="0" lineWidth="1" lineWidthDot="1" frameKind="1" topEdge="false" lineWidthUP="0" lineWidthDotUP="1" lineTypeUP="0" bottomEdge="true" lineWidthDN="1" lineWidthDotDN="1" lineTypeDN="0" leftEdge="true" lineWidthL="1" lineWidthDotL="1" lineTypeL="0" rightEdge="true" lineWidthR="1" lineWidthDotR="1" lineTypeR="0" cornerType="0" leftUpperCorner="true" leftLowerCorner="true" rightUpperCorner="true" rightLowerCorner="true" cornerRadius="50" direction="0" frmCompatible="true" graphicMode="false" curvePattern="0" curveTileType="0" curveTileLineWidth="4" curveTileLineDist="64" curveGradientI="0" curveColor1="1" curveColor2="1" fillingType="0" grayScaleType="0" lineTileType="0" tileLineWidth="4" tileLineDistance="64" tileImageFilePath="" tileImageFitting="false" gradientX1="0" gradientY1="0" gradientX2="100" gradientY2="0" gradientCyclic="false" gradientI="0" gradientX="0" roundGradientX="1000" roundGradientY="1000" roundGradientRadius="2000" interiorBgColor="1" gradientColor1="1" gradientColor2="1" wordPaint="false" forSubFormOrRecord="true" commonPage="true" layerNumber="0" groupIndex="0" colorIndexes="0" paintColorIndexes="0" subProperties="true" />
      <Field name="TOTAL_NO1" strComment="トータル1" strLinkFieldName="" x="254" y="651" charCount="3" charCountDisp="3" bufferLen="0" charType="0" pitch="0.1666666666666714" fixPitch="false" fontNum="1" hanFontNum="0" point="8" type="0" editStyle="1" strCalcFormula="" strEditFormula="" vertRatio="1" vertRatioN="1" horzRatio="1" horzRatioN="1" direction="0" rotation="0" maskFlag="false" lockFlag="false" keyNum="0" isDescending="false" pageFeed="false" strHeaderRecName="" strTotalRecName="" onlyFirstPage="false" onlyLastPage="false" printLastOfGroup="false" groupSuppress="false" groupSuppressFree="false" centeringOnDuplicated="false" suppressLineOnDuplicated="false" clearAccumulateCount="false" clearPageCount="false" frmCompatible="true" graphicMode="false" bold="false" italic="false" outline="false" outlineWidth="1" strImage="" whiteChar="false" shadow="false" useGradientPaint="false" colorGradient1="1" colorGradient2="1" gradientKind="0" annotationLevel="0" commonPage="true" layerNumber="31" locked="false" groupIndex="0" colorIndexes="0" />
      <Field name="SCHOOL_NAME1" strComment="学校名称1" strLinkFieldName="" x="363" y="651" charCount="20" charCountDisp="20" bufferLen="0" charType="0" pitch="0" fixPitch="false" fontNum="1" hanFontNum="0" point="8" type="0" editStyle="0" strCalcFormula="" strEditFormula="" vertRatio="1" vertRatioN="1" horzRatio="1" horzRatioN="1" direction="0" rotation="0" maskFlag="false" lockFlag="false" keyNum="0" isDescending="false" pageFeed="false" strHeaderRecName="" strTotalRecName="" onlyFirstPage="false" onlyLastPage="false" printLastOfGroup="false" groupSuppress="false" groupSuppressFree="false" centeringOnDuplicated="false" suppressLineOnDuplicated="false" clearAccumulateCount="false" clearPageCount="false" frmCompatible="true" graphicMode="false" bold="false" italic="false" outline="false" outlineWidth="1" strImage="" whiteChar="false" shadow="false" useGradientPaint="false" colorGradient1="1" colorGradient2="1" gradientKind="0" annotationLevel="0" commonPage="true" layerNumber="31" locked="false" groupIndex="0" colorIndexes="0" />
      <Field name="COURSE1" strComment="課程1" strLinkFieldName="" x="860" y="651" charCount="10" charCountDisp="10" bufferLen="0" charType="0" pitch="0.08641975308641905" fixPitch="false" fontNum="1" hanFontNum="0" point="8" type="0" editStyle="0" strCalcFormula="" strEditFormula="" vertRatio="1" vertRatioN="1" horzRatio="1" horzRatioN="1" direction="0" rotation="0" maskFlag="false" lockFlag="false" keyNum="0" isDescending="false" pageFeed="false" strHeaderRecName="" strTotalRecName="" onlyFirstPage="false" onlyLastPage="false" printLastOfGroup="false" groupSuppress="false" groupSuppressFree="false" centeringOnDuplicated="false" suppressLineOnDuplicated="false" clearAccumulateCount="false" clearPageCount="false" frmCompatible="true" graphicMode="false" bold="false" italic="false" outline="false" outlineWidth="1" strImage="" whiteChar="false" shadow="false" useGradientPaint="false" colorGradient1="1" colorGradient2="1" gradientKind="0" annotationLevel="0" commonPage="true" layerNumber="31" locked="false" groupIndex="0" colorIndexes="0" />
      <Field name="NAME1" strComment="氏名1" strLinkFieldName="" x="1135" y="651" charCount="20" charCountDisp="20" bufferLen="0" charType="0" pitch="0" fixPitch="false" fontNum="1" hanFontNum="0" point="8" type="0" editStyle="0" strCalcFormula="" strEditFormula="" vertRatio="1" vertRatioN="1" horzRatio="1" horzRatioN="1" direction="0" rotation="0" maskFlag="false" lockFlag="false" keyNum="0" isDescending="false" pageFeed="false" strHeaderRecName="" strTotalRecName="" onlyFirstPage="false" onlyLastPage="false" printLastOfGroup="false" groupSuppress="false" groupSuppressFree="false" centeringOnDuplicated="false" suppressLineOnDuplicated="false" clearAccumulateCount="false" clearPageCount="false" frmCompatible="true" graphicMode="false" bold="false" italic="false" outline="false" outlineWidth="1" strImage="" whiteChar="false" shadow="false" useGradientPaint="false" colorGradient1="1" colorGradient2="1" gradientKind="0" annotationLevel="0" commonPage="true" layerNumber="31" locked="false" groupIndex="0" colorIndexes="0" />
      <Field name="GRADE1" strComment="学年1" strLinkFieldName="" x="1621" y="651" charCount="2" charCountDisp="2" bufferLen="0" charType="0" pitch="0" fixPitch="false" fontNum="1" hanFontNum="0" point="8" type="0" editStyle="1" strCalcFormula="" strEditFormula="" vertRatio="1" vertRatioN="1" horzRatio="1" horzRatioN="1" direction="0" rotation="0" maskFlag="false" lockFlag="false" keyNum="0" isDescending="false" pageFeed="false" strHeaderRecName="" strTotalRecName="" onlyFirstPage="false" onlyLastPage="false" printLastOfGroup="false" groupSuppress="false" groupSuppressFree="false" centeringOnDuplicated="false" suppressLineOnDuplicated="false" clearAccumulateCount="false" clearPageCount="false" frmCompatible="true" graphicMode="false" bold="false" italic="false" outline="false" outlineWidth="1" strImage="" whiteChar="false" shadow="false" useGradientPaint="false" colorGradient1="1" colorGradient2="1" gradientKind="0" annotationLevel="0" commonPage="true" layerNumber="31" locked="false" groupIndex="0" colorIndexes="0" />
      <Field name="PNO1_1" strComment="修学生番号その1_1" strLinkFieldName="" x="1705" y="651" charCount="7" charCountDisp="7" bufferLen="0" charType="0" pitch="0.07407407407407618" fixPitch="false" fontNum="1" hanFontNum="0" point="8" type="0" editStyle="1" strCalcFormula="" strEditFormula="" vertRatio="1" vertRatioN="1" horzRatio="1" horzRatioN="1" direction="0" rotation="0" maskFlag="false" lockFlag="false" keyNum="0" isDescending="false" pageFeed="false" strHeaderRecName="" strTotalRecName="" onlyFirstPage="false" onlyLastPage="false" printLastOfGroup="false" groupSuppress="false" groupSuppressFree="false" centeringOnDuplicated="false" suppressLineOnDuplicated="false" clearAccumulateCount="false" clearPageCount="false" frmCompatible="true" graphicMode="false" bold="false" italic="false" outline="false" outlineWidth="1" strImage="" whiteChar="false" shadow="false" useGradientPaint="false" colorGradient1="1" colorGradient2="1" gradientKind="0" annotationLevel="0" commonPage="true" layerNumber="31" locked="false" groupIndex="0" colorIndexes="0" />
      <Field name="LOAN_HOPE_MONEY1_1" strComment="貸与希望額その１" strLinkFieldName="" x="1903" y="651" charCount="7" charCountDisp="7" bufferLen="0" charType="0" pitch="0.07407407407407618" fixPitch="false" fontNum="1" hanFontNum="0" point="8" type="0" editStyle="1" strCalcFormula="" strEditFormula="FORMAT2(LOAN_HOPE_MONEY1_1,&quot;ZZZ,ZZ9&quot;)" vertRatio="1" vertRatioN="1" horzRatio="1" horzRatioN="1" direction="0" rotation="0" maskFlag="false" lockFlag="false" keyNum="0" isDescending="false" pageFeed="false" strHeaderRecName="" strTotalRecName="" onlyFirstPage="false" onlyLastPage="false" printLastOfGroup="false" groupSuppress="false" groupSuppressFree="false" centeringOnDuplicated="false" suppressLineOnDuplicated="false" clearAccumulateCount="false" clearPageCount="false" frmCompatible="true" graphicMode="false" bold="false" italic="false" outline="false" outlineWidth="1" strImage="" whiteChar="false" shadow="false" useGradientPaint="false" colorGradient1="1" colorGradient2="1" gradientKind="0" annotationLevel="0" commonPage="true" layerNumber="31" locked="false" groupIndex="0" colorIndexes="0" />
      <Field name="LOAN_TFDAY1" strComment="貸与期間　自1" strLinkFieldName="" x="2099" y="651" charCount="9" charCountDisp="9" bufferLen="0" charType="0" pitch="0" fixPitch="false" fontNum="1" hanFontNum="0" point="8" type="0" editStyle="0" strCalcFormula="" strEditFormula="" vertRatio="1" vertRatioN="1" horzRatio="1" horzRatioN="1" direction="0" rotation="0" maskFlag="false" lockFlag="false" keyNum="0" isDescending="false" pageFeed="false" strHeaderRecName="" strTotalRecName="" onlyFirstPage="false" onlyLastPage="false" printLastOfGroup="false" groupSuppress="false" groupSuppressFree="false" centeringOnDuplicated="false" suppressLineOnDuplicated="false" clearAccumulateCount="false" clearPageCount="false" frmCompatible="true" graphicMode="false" bold="false" italic="false" outline="false" outlineWidth="1" strImage="" whiteChar="false" shadow="false" useGradientPaint="false" colorGradient1="1" colorGradient2="1" gradientKind="0" annotationLevel="0" commonPage="true" layerNumber="31" locked="false" groupIndex="0" colorIndexes="0" />
      <Field name="LOAN_TTDAY1" strComment="貸与期間　至1" strLinkFieldName="" x="2335" y="651" charCount="9" charCountDisp="9" bufferLen="0" charType="0" pitch="0" fixPitch="false" fontNum="1" hanFontNum="0" point="8" type="0" editStyle="0" strCalcFormula="" strEditFormula="" vertRatio="1" vertRatioN="1" horzRatio="1" horzRatioN="1" direction="0" rotation="0" maskFlag="false" lockFlag="false" keyNum="0" isDescending="false" pageFeed="false" strHeaderRecName="" strTotalRecName="" onlyFirstPage="false" onlyLastPage="false" printLastOfGroup="false" groupSuppress="false" groupSuppressFree="false" centeringOnDuplicated="false" suppressLineOnDuplicated="false" clearAccumulateCount="false" clearPageCount="false" frmCompatible="true" graphicMode="false" bold="false" italic="false" outline="false" outlineWidth="1" strImage="" whiteChar="false" shadow="false" useGradientPaint="false" colorGradient1="1" colorGradient2="1" gradientKind="0" annotationLevel="0" commonPage="true" layerNumber="31" locked="false" groupIndex="0" colorIndexes="0" />
      <Field name="PNO1_2" strComment="修学生番号その２1" strLinkFieldName="" x="2573" y="651" charCount="9" charCountDisp="9" bufferLen="0" charType="0" pitch="0" fixPitch="false" fontNum="1" hanFontNum="0" point="8" type="0" editStyle="1" strCalcFormula="" strEditFormula="" vertRatio="1" vertRatioN="1" horzRatio="1" horzRatioN="1" direction="0" rotation="0" maskFlag="false" lockFlag="false" keyNum="0" isDescending="false" pageFeed="false" strHeaderRecName="" strTotalRecName="" onlyFirstPage="false" onlyLastPage="false" printLastOfGroup="false" groupSuppress="false" groupSuppressFree="false" centeringOnDuplicated="false" suppressLineOnDuplicated="false" clearAccumulateCount="false" clearPageCount="false" frmCompatible="true" graphicMode="false" bold="false" italic="false" outline="false" outlineWidth="1" strImage="" whiteChar="false" shadow="false" useGradientPaint="false" colorGradient1="1" colorGradient2="1" gradientKind="0" annotationLevel="0" commonPage="true" layerNumber="31" locked="false" groupIndex="0" colorIndexes="0" />
      <Field name="LOAN_HOPE_MONEY1_2" strComment="貸与希望額1" strLinkFieldName="" x="2811" y="651" charCount="9" charCountDisp="9" bufferLen="0" charType="0" pitch="0" fixPitch="false" fontNum="1" hanFontNum="0" point="8" type="0" editStyle="1" strCalcFormula="" strEditFormula="FORMAT2(LOAN_HOPE_MONEY1_2,&quot;Z,ZZZ,ZZ9&quot;)" vertRatio="1" vertRatioN="1" horzRatio="1" horzRatioN="1" direction="0" rotation="0" maskFlag="false" lockFlag="false" keyNum="0" isDescending="false" pageFeed="false" strHeaderRecName="" strTotalRecName="" onlyFirstPage="false" onlyLastPage="false" printLastOfGroup="false" groupSuppress="false" groupSuppressFree="false" centeringOnDuplicated="false" suppressLineOnDuplicated="false" clearAccumulateCount="false" clearPageCount="false" frmCompatible="true" graphicMode="false" bold="false" italic="false" outline="false" outlineWidth="1" strImage="" whiteChar="false" shadow="false" useGradientPaint="false" colorGradient1="1" colorGradient2="1" gradientKind="0" annotationLevel="0" commonPage="true" layerNumber="31" locked="false" groupIndex="0" colorIndexes="0" />
      <Field name="REMARK" strComment="備考" strLinkFieldName="" x="3053" y="651" charCount="6" charCountDisp="6" bufferLen="0" charType="0" pitch="0" fixPitch="false" fontNum="1" hanFontNum="0" point="8" type="0" editStyle="0" strCalcFormula="" strEditFormula="" vertRatio="1" vertRatioN="1" horzRatio="1" horzRatioN="1" direction="0" rotation="0" maskFlag="false" lockFlag="false" keyNum="0" isDescending="false" pageFeed="false" strHeaderRecName="" strTotalRecName="" onlyFirstPage="false" onlyLastPage="false" printLastOfGroup="false" groupSuppress="false" groupSuppressFree="false" centeringOnDuplicated="false" suppressLineOnDuplicated="false" clearAccumulateCount="false" clearPageCount="false" frmCompatible="true" graphicMode="false" bold="false" italic="false" outline="false" outlineWidth="1" strImage="" whiteChar="false" shadow="false" useGradientPaint="false" colorGradient1="1" colorGradient2="1" gradientKind="0" annotationLevel="0" commonPage="true" layerNumber="31" locked="false" groupIndex="0" colorIndexes="0" />
      <Line name="Line15" x1="336" y1="632" x2="336" y2="710" lineWidth="1" lineWidthDot="1" lineType="0" frmCompatible="true" graphicMode="false" arrowPos="0" arrowSide="0" arrowType="0" arrowAngle="30" arrowSize="80" curvePattern="0" curveTileType="0" curveTileLineWidth="4" curveTileLineDist="64" curveColor1="1" curveColor2="1" hvOnly="true" commonPage="false" layerNumber="21" locked="false" groupIndex="0" pageFlags="true" colorIndexes="0" />
      <Line name="Line16" x1="830" y1="632" x2="830" y2="710" lineWidth="1" lineWidthDot="1" lineType="0" frmCompatible="true" graphicMode="false" arrowPos="0" arrowSide="0" arrowType="0" arrowAngle="30" arrowSize="80" curvePattern="0" curveTileType="0" curveTileLineWidth="4" curveTileLineDist="64" curveColor1="1" curveColor2="1" hvOnly="true" commonPage="false" layerNumber="21" locked="false" groupIndex="0" pageFlags="true" colorIndexes="0" />
      <Line name="Line17" x1="1108" y1="632" x2="1108" y2="710" lineWidth="1" lineWidthDot="1" lineType="0" frmCompatible="true" graphicMode="false" arrowPos="0" arrowSide="0" arrowType="0" arrowAngle="30" arrowSize="80" curvePattern="0" curveTileType="0" curveTileLineWidth="4" curveTileLineDist="64" curveColor1="1" curveColor2="1" hvOnly="true" commonPage="false" layerNumber="21" locked="false" groupIndex="0" pageFlags="true" colorIndexes="0" />
      <Line name="Line18" x1="1602" y1="632" x2="1602" y2="710" lineWidth="1" lineWidthDot="1" lineType="0" frmCompatible="true" graphicMode="false" arrowPos="0" arrowSide="0" arrowType="0" arrowAngle="30" arrowSize="80" curvePattern="0" curveTileType="0" curveTileLineWidth="4" curveTileLineDist="64" curveColor1="1" curveColor2="1" hvOnly="true" commonPage="false" layerNumber="21" locked="false" groupIndex="0" pageFlags="true" colorIndexes="0" />
      <Line name="Line19" x1="1682" y1="632" x2="1682" y2="710" lineWidth="1" lineWidthDot="1" lineType="0" frmCompatible="true" graphicMode="false" arrowPos="0" arrowSide="0" arrowType="0" arrowAngle="30" arrowSize="80" curvePattern="0" curveTileType="0" curveTileLineWidth="4" curveTileLineDist="64" curveColor1="1" curveColor2="1" hvOnly="true" commonPage="false" layerNumber="21" locked="false" groupIndex="0" pageFlags="true" colorIndexes="0" />
      <Line name="Line20" x1="1880" y1="632" x2="1880" y2="710" lineWidth="1" lineWidthDot="1" lineType="0" frmCompatible="true" graphicMode="false" arrowPos="0" arrowSide="0" arrowType="0" arrowAngle="30" arrowSize="80" curvePattern="0" curveTileType="0" curveTileLineWidth="4" curveTileLineDist="64" curveColor1="1" curveColor2="1" hvOnly="true" commonPage="false" layerNumber="21" locked="false" groupIndex="0" pageFlags="true" colorIndexes="0" />
      <Line name="Line21" x1="2078" y1="632" x2="2078" y2="710" lineWidth="1" lineWidthDot="1" lineType="0" frmCompatible="true" graphicMode="false" arrowPos="0" arrowSide="0" arrowType="0" arrowAngle="30" arrowSize="80" curvePattern="0" curveTileType="0" curveTileLineWidth="4" curveTileLineDist="64" curveColor1="1" curveColor2="1" hvOnly="true" commonPage="false" layerNumber="21" locked="false" groupIndex="0" pageFlags="true" colorIndexes="0" />
      <Line name="Line22" x1="2316" y1="632" x2="2316" y2="710" lineWidth="1" lineWidthDot="1" lineType="0" frmCompatible="true" graphicMode="false" arrowPos="0" arrowSide="0" arrowType="0" arrowAngle="30" arrowSize="80" curvePattern="0" curveTileType="0" curveTileLineWidth="4" curveTileLineDist="64" curveColor1="1" curveColor2="1" hvOnly="true" commonPage="false" layerNumber="21" locked="false" groupIndex="0" pageFlags="true" colorIndexes="0" />
      <Line name="Line23" x1="2554" y1="632" x2="2554" y2="710" lineWidth="1" lineWidthDot="1" lineType="0" frmCompatible="true" graphicMode="false" arrowPos="0" arrowSide="0" arrowType="0" arrowAngle="30" arrowSize="80" curvePattern="0" curveTileType="0" curveTileLineWidth="4" curveTileLineDist="64" curveColor1="1" curveColor2="1" hvOnly="true" commonPage="false" layerNumber="21" locked="false" groupIndex="0" pageFlags="true" colorIndexes="0" />
      <Line name="Line24" x1="2792" y1="632" x2="2792" y2="710" lineWidth="1" lineWidthDot="1" lineType="0" frmCompatible="true" graphicMode="false" arrowPos="0" arrowSide="0" arrowType="0" arrowAngle="30" arrowSize="80" curvePattern="0" curveTileType="0" curveTileLineWidth="4" curveTileLineDist="64" curveColor1="1" curveColor2="1" hvOnly="true" commonPage="false" layerNumber="21" locked="false" groupIndex="0" pageFlags="true" colorIndexes="0" />
      <Line name="Line25" x1="3028" y1="632" x2="3028" y2="710" lineWidth="1" lineWidthDot="1" lineType="0" frmCompatible="true" graphicMode="false" arrowPos="0" arrowSide="0" arrowType="0" arrowAngle="30" arrowSize="80" curvePattern="0" curveTileType="0" curveTileLineWidth="4" curveTileLineDist="64" curveColor1="1" curveColor2="1" hvOnly="true" commonPage="false" layerNumber="21" locked="false" groupIndex="0" pageFlags="true" colorIndexes="0" />
    </Record>
  </SubForm>
  <GridSetting nGridStyle="1" dGridSpacing="5.0" dGridSpacingX="2.5" dGridSpacingY="2.5" gridUnit="1" gridUnitX="1" gridUnitY="1" gridSpacingMolecular="1" gridSpacingMolecularX="1" gridSpacingMolecularY="1" gridSpacingDenominator="1.0" gridSpacingDenominatorX="1.0" gridSpacingDenominatorY="1.0" gridSettingSeparateVH="true" adjustCharPitchToGrid="false" gridAdjustPos4CharX="0.0" gridAdjustPos4CharY="0.0" nGridLocationMode="3" gridIsDisplayed="true" dInputGridSpacing="10.0" dInputGridSpacingX="10.0" dInputGridSpacingY="10.0" />
</FormData>

